tvb_ext_unicore/__init__.py
tvb_ext_unicore/_version.py
tvb_ext_unicore/exceptions.py
tvb_ext_unicore/handlers.py
tvb_ext_unicore/utils.py
tvb_ext_unicore/logger/__init__.py
tvb_ext_unicore/logger/builder.py
tvb_ext_unicore/logger/logging.conf
tvb_ext_unicore/tests/__init__.py
tvb_ext_unicore/tests/test_unicore_wrapper.py
tvb_ext_unicore/unicore_wrapper/__init__.py
tvb_ext_unicore/unicore_wrapper/job_dto.py
tvb_ext_unicore/unicore_wrapper/unicore_wrapper.py
tvb_ext_unicore-3.0.0.data/data/etc/jupyter/jupyter_server_config.d/tvbextunicore.json
tvb_ext_unicore-3.0.0.data/data/share/jupyter/labextensions/tvb-ext-unicore/package.json
tvb_ext_unicore-3.0.0.data/data/share/jupyter/labextensions/tvb-ext-unicore/static/496.a82641f04a7bc7f8096c.js
tvb_ext_unicore-3.0.0.data/data/share/jupyter/labextensions/tvb-ext-unicore/static/728.838f5321c3558c104f7b.js
tvb_ext_unicore-3.0.0.data/data/share/jupyter/labextensions/tvb-ext-unicore/static/remoteEntry.03f70054ab7fcaebf55f.js
tvb_ext_unicore-3.0.0.data/data/share/jupyter/labextensions/tvb-ext-unicore/static/style.js
tvb_ext_unicore-3.0.0.data/data/share/jupyter/labextensions/tvb-ext-unicore/static/third-party-licenses.json
tvb_ext_unicore-3.0.0.data/data/share/jupyter/labextensions/tvb-ext-unicore/install.json
tvb_ext_unicore-3.0.0.dist-info/METADATA
tvb_ext_unicore-3.0.0.dist-info/WHEEL
tvb_ext_unicore-3.0.0.dist-info/licenses/AUTHORS
tvb_ext_unicore-3.0.0.dist-info/licenses/LICENSE
tvb_ext_unicore-3.0.0.dist-info/RECORD
