Metadata-Version: 2.3
Name: tvb-ext-unicore
Version: 3.0.0
Summary: TVB Widgets - A Unicore Lab extension
Project-URL: Homepage, https://github.com/the-virtual-brain/tvb-ext-unicore
Project-URL: Bug Tracker, https://tvb-projects.atlassian.net/
Project-URL: Repository, https://github.com/the-virtual-brain/tvb-ext-unicore.git
Author-email: TVB Widgets Team <tvb.admin@thevirtualbrain.org>
License: GNU General Public License v3.0 or later
License-File: AUTHORS
License-File: LICENSE
Keywords: jupyter,jupyterlab,jupyterlab-extension
Classifier: Framework :: Jupyter
Classifier: Framework :: Jupyter :: JupyterLab
Classifier: Framework :: Jupyter :: JupyterLab :: 4
Classifier: Framework :: Jupyter :: JupyterLab :: Extensions
Classifier: Framework :: Jupyter :: JupyterLab :: Extensions :: Prebuilt
Classifier: License :: OSI Approved :: BSD License
Classifier: Programming Language :: Python
Classifier: Programming Language :: Python :: 3
Classifier: Programming Language :: Python :: 3.8
Classifier: Programming Language :: Python :: 3.9
Classifier: Programming Language :: Python :: 3.10
Classifier: Programming Language :: Python :: 3.11
Classifier: Programming Language :: Python :: 3.12
Requires-Python: >=3.8
Requires-Dist: jupyter-server<3,>=2.0.1
Requires-Dist: pyunicore>=1.0
Provides-Extra: test
Requires-Dist: coverage; extra == 'test'
Requires-Dist: pytest; extra == 'test'
Requires-Dist: pytest-asyncio; extra == 'test'
Requires-Dist: pytest-cov; extra == 'test'
Requires-Dist: pytest-jupyter[server]>=0.6.0; extra == 'test'
